odoo/addons/mass_mailing_resend/README.rst
odoo/addons/mass_mailing_resend/__init__.py
odoo/addons/mass_mailing_resend/__manifest__.py
odoo/addons/mass_mailing_resend/i18n/ca.po
odoo/addons/mass_mailing_resend/i18n/de.po
odoo/addons/mass_mailing_resend/i18n/es.po
odoo/addons/mass_mailing_resend/i18n/fr.po
odoo/addons/mass_mailing_resend/i18n/mass_mailing_resend.pot
odoo/addons/mass_mailing_resend/i18n/sl.po
odoo/addons/mass_mailing_resend/models/__init__.py
odoo/addons/mass_mailing_resend/models/mass_mailing.py
odoo/addons/mass_mailing_resend/readme/CONTRIBUTORS.rst
odoo/addons/mass_mailing_resend/readme/DESCRIPTION.rst
odoo/addons/mass_mailing_resend/readme/ROADMAP.rst
odoo/addons/mass_mailing_resend/readme/USAGE.rst
odoo/addons/mass_mailing_resend/static/description/icon.png
odoo/addons/mass_mailing_resend/static/description/icon.svg
odoo/addons/mass_mailing_resend/static/description/index.html
odoo/addons/mass_mailing_resend/tests/__init__.py
odoo/addons/mass_mailing_resend/tests/test_mass_mailing_resend.py
odoo/addons/mass_mailing_resend/views/mass_mailing_views.xml
odoo11_addon_mass_mailing_resend-11.0.1.0.0.99.dev5.dist-info/METADATA
odoo11_addon_mass_mailing_resend-11.0.1.0.0.99.dev5.dist-info/WHEEL
odoo11_addon_mass_mailing_resend-11.0.1.0.0.99.dev5.dist-info/top_level.txt
odoo11_addon_mass_mailing_resend-11.0.1.0.0.99.dev5.dist-info/RECORD
